ftm_geocode/__init__.py
ftm_geocode/cache.py
ftm_geocode/cli.py
ftm_geocode/formatting.py
ftm_geocode/ftm.py
ftm_geocode/geocode.py
ftm_geocode/io.py
ftm_geocode/model.py
ftm_geocode/nuts.py
ftm_geocode/parsing.py
ftm_geocode/settings.py
ftm_geocode/tasks.py
ftm_geocode/util.py
ftm_geocode-4.3.0.dist-info/METADATA
ftm_geocode-4.3.0.dist-info/WHEEL
ftm_geocode-4.3.0.dist-info/entry_points.txt
ftm_geocode-4.3.0.dist-info/licenses/LICENSE
ftm_geocode-4.3.0.dist-info/licenses/NOTICE
ftm_geocode-4.3.0.dist-info/RECORD
