Metadata-Version: 2.4
Name: ftm-geocode
Version: 4.3.0
Summary: Parsing and geocoding addresses for followthemoney entities powered by libpostal
License: AGPLv3+
License-File: LICENSE
License-File: NOTICE
Author: Simon Wörpel
Author-email: simon.woerpel@pm.me
Requires-Python: >=3.11,<4
Classifier: Intended Audience :: Developers
Classifier: Operating System :: OS Independent
Classifier: Programming Language :: Python
Classifier: Programming Language :: Python :: 3.11
Classifier: Programming Language :: Python :: 3.12
Classifier: Programming Language :: Python :: 3.13
Provides-Extra: openaleph
Provides-Extra: postal
Requires-Dist: anystore (>=0.4.0,<0.5.0)
Requires-Dist: ftmq (>=4.3.3,<5.0.0)
Requires-Dist: geopandas (>=1.1.0,<2.0.0)
Requires-Dist: geopy (>=2.4.1,<3.0.0)
Requires-Dist: lazy-import (>=0.2.2,<0.3.0)
Requires-Dist: openaleph-procrastinate (>=5.1.2,<6.0.0) ; extra == "openaleph"
Requires-Dist: postal (>=1.1.11,<2.0.0) ; extra == "postal"
Project-URL: Documentation, https://docs.investigraph.dev/lib/ftm-geocode
Project-URL: Homepage, https://docs.investigraph.dev/lib/ftm-geocode
Project-URL: Issues, https://github.com/dataresearchcenter/ftm-geocode/issues
Project-URL: Repository, https://github.com/dataresearchcenter/ftm-geocode
